{
    "AX": {
        "error": 0.00028443255041385755,
        "fit": "Weighted Mean",
        "reference_data": {
            "es": [
                0.00035690938971743045,
                0.0003488649873103891,
                0.00035595917083774704,
                0.0003590372384851125,
                0.0003430692162565926,
                0.0005316992121041111,
                0.0003435182201169427,
                0.0005181182182880574,
                0.00035919778299571336,
                0.00047106466734154193,
                0.00035914260824453293,
                0.00034647268340806713,
                0.00036352405863358193,
                0.0003451944229275399,
                0.0004884296913365383,
                0.0003538222587590369,
                0.0003471641376156625,
                0.00034260152555527003
            ],
            "vs": [
                1.003027442949503,
                1.0024540828115107,
                1.0016991178117127,
                1.001980934902053,
                1.0015965191075094,
                1.001237123643693,
                1.0027381344646358,
                1.0018807609421252,
                1.0036655602151832,
                1.003791141078804,
                1.005383070748273,
                1.0041268499902014,
                1.0037310326343445,
                1.003127690527298,
                0.9999837103769179,
                1.0013203182921784,
                1.0017970013924538,
                1.0013123237680006
            ],
            "xs": [
                1524684168.0,
                1524689963.0,
                1524695808.0,
                1524703221.0,
                1524709229.0,
                1524716538.0,
                1524721933.0,
                1524728172.0,
                1524735030.0,
                1524741736.0,
                1524748222.0,
                1524754670.0,
                1524760154.0,
                1524767847.0,
                1524773830.0,
                1524778663.0,
                1524784624.0,
                1524790964.0
            ]
        },
        "reference_detector": "rad40",
        "references": [
            {
                "exclude": "ok",
                "record_id": "c-02-J-3350",
                "uuid": "e659529f-288d-4441-a8d9-b31dbd84ec54"
            },
            {
                "exclude": "ok",
                "record_id": "c-02-J-3351",
                "uuid": "193b2558-1b1c-4b7a-aaa0-76e2c04a8d56"
            },
            {
                "exclude": "ok",
                "record_id": "c-02-J-3352",
                "uuid": "9b56f968-9c37-4c7b-b98d-bb6b3a4e6023"
            },
            {
                "exclude": "ok",
                "record_id": "c-02-J-3353",
                "uuid": "2ef0dabd-638d-4297-b964-333d71248f9b"
            },
            {
                "exclude": "ok",
                "record_id": "c-02-J-3354",
                "uuid": "1124c0e1-99f5-4f27-9215-89b153b2a304"
            },
            {
                "exclude": "ok",
                "record_id": "c-02-J-3355",
                "uuid": "fbd78b86-555e-4047-8f14-c633d6a11030"
            },
            {
                "exclude": "ok",
                "record_id": "c-02-J-3356",
                "uuid": "3ec6af15-8e6f-4073-b39b-193acd583da2"
            },
            {
                "exclude": "ok",
                "record_id": "c-02-J-3357",
                "uuid": "fba6ad84-5bbf-40fc-9896-771a61292fdd"
            },
            {
                "exclude": "ok",
                "record_id": "c-02-J-3358",
                "uuid": "2c5cf746-f8bf-4879-923e-efe459872a83"
            },
            {
                "exclude": "ok",
                "record_id": "c-02-J-3359",
                "uuid": "5d4a3204-21fc-4587-acbf-0f076a395e20"
            },
            {
                "exclude": "ok",
                "record_id": "c-02-J-3360",
                "uuid": "0b9bf27c-4e5e-43ca-9df8-0a1ed58fc76a"
            },
            {
                "exclude": "ok",
                "record_id": "c-02-J-3361",
                "uuid": "438ebfe1-7472-40a2-b200-241588e05ca6"
            },
            {
                "exclude": "ok",
                "record_id": "c-02-J-3362",
                "uuid": "b283c6a8-efec-46c6-90c3-ab32399d8ee1"
            },
            {
                "exclude": "ok",
                "record_id": "c-02-J-3363",
                "uuid": "d6b5083c-d210-4b05-9029-530326314e87"
            },
            {
                "exclude": "ok",
                "record_id": "c-02-J-3364",
                "uuid": "b8de74a6-891c-4df7-86e4-41c2aeb1e982"
            },
            {
                "exclude": "ok",
                "record_id": "c-02-J-3365",
                "uuid": "b371400a-30c4-4d2d-b46b-76bfbd0738d9"
            },
            {
                "exclude": "ok",
                "record_id": "c-02-J-3366",
                "uuid": "5adb80c7-e05e-4698-b6b6-86653a3ebf89"
            },
            {
                "exclude": "ok",
                "record_id": "c-02-J-3367",
                "uuid": "dbdbe23a-ad16-4448-a2d8-51e5796d82e9"
            }
        ],
        "reviewed": true,
        "standard_ratio": 12.30815,
        "value": 1.002279556821345
    },
    "CDD": {
        "error": 0.000539297817598772,
        "fit": "Weighted Mean",
        "reference_data": {
            "es": [
                0.0016593612453560933,
                0.0015577981087695526,
                0.0016493341506772488,
                0.0016027461165910933,
                0.00154385045337403,
                0.0015974680407994928,
                0.0017645720823818325,
                0.001592189334792108,
                0.0016241430166362464
            ],
            "vs": [
                1.0079450435847892,
                1.0076181564621007,
                1.0070388494069942,
                1.012457767645802,
                1.008992276950983,
                1.0083809752993969,
                1.009451237513536,
                1.0081653582998191,
                1.0082278578965382
            ],
            "xs": [
                1524683598.0,
                1524696828.0,
                1524710662.0,
                1524724194.0,
                1524737232.0,
                1524750882.0,
                1524764728.0,
                1524770802.0,
                1524782630.0
            ]
        },
        "reference_detector": "H1",
        "references": [
            {
                "exclude": "ok",
                "record_id": "a-02-J-423",
                "uuid": "d08140d6-386a-406d-9d75-a4eb5eb0c9ed"
            },
            {
                "exclude": "ok",
                "record_id": "a-02-J-424",
                "uuid": "cb76648e-4ed9-4172-a669-52ebe5816c4b"
            },
            {
                "exclude": "ok",
                "record_id": "a-02-J-425",
                "uuid": "a604defb-b5a8-4d32-84b8-df0d001ca93d"
            },
            {
                "exclude": "ok",
                "record_id": "a-02-J-426",
                "uuid": "5694e146-be8c-4bff-998a-55b12c603164"
            },
            {
                "exclude": "ok",
                "record_id": "a-02-J-427",
                "uuid": "0f27acb3-fed4-4326-9f56-614f0e6103b2"
            },
            {
                "exclude": "ok",
                "record_id": "a-02-J-428",
                "uuid": "3fef0c3a-8941-4cd6-a30e-b79e2582a233"
            },
            {
                "exclude": "ok",
                "record_id": "a-02-J-429",
                "uuid": "65838c49-318b-451a-a486-4be1e6506395"
            },
            {
                "exclude": "ok",
                "record_id": "a-02-J-430",
                "uuid": "b7ba8be1-a402-4482-a8d4-d92cacbc5449"
            },
            {
                "exclude": "ok",
                "record_id": "a-02-J-431",
                "uuid": "2fc0949e-0f36-4fcf-9568-cfc504b3e636"
            }
        ],
        "reviewed": true,
        "standard_ratio": 295.5,
        "value": 1.0086945354162467
    },
    "H1": {
        "error": 1e-20,
        "fit": "default",
        "references": [],
        "value": 1.0
    },
    "H2": {
        "error": 1e-20,
        "fit": "default",
        "references": [],
        "value": 1.0
    },
    "L1": {
        "error": 1e-20,
        "fit": "default",
        "references": [],
        "value": 1.0
    },
    "L2": {
        "error": 1e-20,
        "fit": "default",
        "references": [],
        "value": 1.0
    }
}