{
    "Ar36": {
        "error": 0.000379914876329973,
        "error_type": "SEM",
        "filter_outliers_dict": {
            "filter_outliers": true,
            "iterations": 1,
            "std_devs": 2
        },
        "fit": "Linear",
        "fn": 113,
        "include_baseline_error": false,
        "n": 120,
        "reviewed": true,
        "value": 0.022552868186267734
    },
    "Ar37": {
        "error": 0.00994307487471458,
        "error_type": "SEM",
        "filter_outliers_dict": {
            "filter_outliers": true,
            "iterations": 1,
            "std_devs": 2
        },
        "fit": "Linear",
        "fn": 117,
        "include_baseline_error": false,
        "n": 120,
        "reviewed": true,
        "value": 1.159285111887261
    },
    "Ar38": {
        "error": 0.006635466073078853,
        "error_type": "SEM",
        "filter_outliers_dict": {
            "filter_outliers": true,
            "iterations": 1,
            "std_devs": 2
        },
        "fit": "Linear",
        "fn": 115,
        "include_baseline_error": false,
        "n": 120,
        "reviewed": true,
        "value": 3.9894938182061583
    },
    "Ar39": {
        "error": 0.03456630002897236,
        "error_type": "SEM",
        "filter_outliers_dict": {
            "filter_outliers": true,
            "iterations": 1,
            "std_devs": 2
        },
        "fit": "Linear",
        "fn": 115,
        "include_baseline_error": false,
        "n": 120,
        "reviewed": true,
        "value": 307.5261052022722
    },
    "Ar40": {
        "error": 0.05963478519933587,
        "error_type": "SEM",
        "filter_outliers_dict": {
            "filter_outliers": true,
            "iterations": 1,
            "std_devs": 2
        },
        "fit": "Linear",
        "fn": 115,
        "include_baseline_error": false,
        "n": 120,
        "reviewed": true,
        "value": 1212.1075545483059
    },
    "Ar41": {
        "error": 0.011638862701571715,
        "error_type": "SEM",
        "filter_outliers_dict": {
            "filter_outliers": true,
            "iterations": 1,
            "std_devs": 2
        },
        "fit": "Average",
        "value": 0.09099570540644919
    }
}